circinus/__init__.py
circinus/__main__.py
circinus/agent.py
circinus/cli.py
circinus/fuzzer.py
circinus/llm.py
circinus/logger.py
circinus/settings.py
circinus/utils.py
circinus-0.0.1.dist-info/LICENSE
circinus-0.0.1.dist-info/METADATA
circinus-0.0.1.dist-info/WHEEL
circinus-0.0.1.dist-info/RECORD
